wikontic/__init__.py
wikontic/create_ontological_triplets_db.py
wikontic/create_triplets_db.py
wikontic/create_wikidata_ontology_db.py
wikontic/utils/__init__.py
wikontic/utils/base_inference_with_db.py
wikontic/utils/dynamic_aligner.py
wikontic/utils/inference_with_db.py
wikontic/utils/openai_utils.py
wikontic/utils/structured_aligner.py
wikontic/utils/structured_inference_with_db.py
wikontic/utils/ontology_mappings/entity_hierarchy.json
wikontic/utils/ontology_mappings/entity_names.json
wikontic/utils/ontology_mappings/entity_type2aliases.json
wikontic/utils/ontology_mappings/entity_type2hierarchy.json
wikontic/utils/ontology_mappings/entity_type2label.json
wikontic/utils/ontology_mappings/enum_entity_ids.json
wikontic/utils/ontology_mappings/enum_prop_ids.json
wikontic/utils/ontology_mappings/label2entity.json
wikontic/utils/ontology_mappings/obj_constraint2prop.json
wikontic/utils/ontology_mappings/prop2aliases.json
wikontic/utils/ontology_mappings/prop2constraints.json
wikontic/utils/ontology_mappings/prop2data_type.json
wikontic/utils/ontology_mappings/prop2label.json
wikontic/utils/ontology_mappings/propid2enum.json
wikontic/utils/ontology_mappings/subj_constraint2prop.json
wikontic/utils/ontology_mappings/subject_object_constraints.json
wikontic/utils/prompts/name_refinement/prompt_choose_relation_wo_entity_types.txt
wikontic/utils/prompts/name_refinement/prompt_choose_relation_wo_entity_types_dialog_bench.txt
wikontic/utils/prompts/name_refinement/rank_object_names.txt
wikontic/utils/prompts/name_refinement/rank_object_names_dialog_bench.txt
wikontic/utils/prompts/name_refinement/rank_object_qualifiers.txt
wikontic/utils/prompts/name_refinement/rank_subject_names.txt
wikontic/utils/prompts/name_refinement/rank_subject_names_dialog_bench.txt
wikontic/utils/prompts/ontology_refinement/prompt_choose_entity_types.txt
wikontic/utils/prompts/ontology_refinement/prompt_choose_relation.txt
wikontic-0.0.7.dist-info/licenses/LICENSE
wikontic-0.0.7.dist-info/METADATA
wikontic-0.0.7.dist-info/WHEEL
wikontic-0.0.7.dist-info/top_level.txt
wikontic-0.0.7.dist-info/RECORD
