Metadata-Version: 2.4
Name: wikontic
Version: 0.0.7
Summary: Extract a knowledge graph with LLM from texts and perform QA over the resulted KG
Author-email: Alla Chepurova <chepurova.data@gmail.com>
License-Expression: MIT
Project-URL: Homepage, https://github.com/screemix/Wikontic
Project-URL: Issues, https://github.com/screemix/Wikontic/issues
Classifier: Programming Language :: Python :: 3
Classifier: Operating System :: OS Independent
Requires-Python: >=3.9
License-File: LICENSE
Requires-Dist: streamlit
Requires-Dist: numpy
Requires-Dist: pyvis
Requires-Dist: python-dotenv
Requires-Dist: pymongo
Requires-Dist: openai
Requires-Dist: tenacity
Requires-Dist: pathlib
Requires-Dist: typing
Requires-Dist: unidecode
Requires-Dist: torch>=2.4.0
Requires-Dist: transformers
Requires-Dist: dataclasses
Requires-Dist: pydantic
Requires-Dist: accelerate
Requires-Dist: langchain
Requires-Dist: langchain_openai
Dynamic: license-file
